todo/cli.py
todo/config.py
todo/model.py
todo/server.py
todo/service.py
mcp_todo-0.0.2.dist-info/METADATA
mcp_todo-0.0.2.dist-info/WHEEL
mcp_todo-0.0.2.dist-info/entry_points.txt
mcp_todo-0.0.2.dist-info/top_level.txt
mcp_todo-0.0.2.dist-info/RECORD
