Metadata-Version: 2.2
Name: mcp-todo
Version: 0.0.2
Summary: A command-line todo application with MCP server capabilities for LLM integration
License: MIT
Keywords: todo,mcp,llm,automation
Classifier: Development Status :: 4 - Beta
Classifier: Intended Audience :: Developers
Classifier: License :: OSI Approved :: MIT License
Classifier: Programming Language :: Python :: 3
Classifier: Programming Language :: Python :: 3.10
Requires-Python: >=3.10
Requires-Dist: click>=8.1.7
Requires-Dist: mcp>=1.0.0
Requires-Dist: toml>=0.10.2
Requires-Dist: pydantic>=2.0.0
Requires-Dist: tabulate>=0.9.0
Requires-Dist: wcwidth>=0.2.13
